omu_chat_twitch/__init__.py
omu_chat_twitch/chat_service.py
omu_chat_twitch/const.py
omu_chat_twitch/version.py
omu_chat_twitch/twitch/__init__.py
omu_chat_twitch/twitch/api.py
omu_chat_twitch/twitch/chat.py
omu_chat_twitch/twitch/command.py
omu_chat_twitch/twitch/gql.py
omu_chat_twitch/twitch/gql_mappings.json
omu_chat_twitch/twitch/helper.py
omu_chat_twitch/twitch/hermes.py
omu_chat_twitch/twitch/pubsub.py
omu_chat_twitch/twitch/types/channelroot_aboutpanel.py
omu_chat_twitch/twitch/types/models.py
omu_chat_twitch/twitch/types/playback_access_token_template.py
omu_chat_twitch/twitch/types/query_variables.py
omu_chat_twitch/twitch/types/stream_metadata.py
omu_chat_twitch/twitch/types/use_view_count.py
omu_chat_twitch/twitch/types/viewer_card.py
omu_chat_twitch-0.9.50.dist-info/METADATA
omu_chat_twitch-0.9.50.dist-info/WHEEL
omu_chat_twitch-0.9.50.dist-info/entry_points.txt
omu_chat_twitch-0.9.50.dist-info/RECORD
